{
  "name": "Beidou",
  "description": "Thủ lĩnh đội thuyền vũ trang \"Nam Thập Tự\", và chị đại hào sång.",
  "vision": "Lôi",
  "weapon": "Trọng Kiếm",
  "rarity": 4,
  "body": "Teen",
  "skillTalents": [
    {
      "name": "Đại Dương",
      "unlock": "Tấn công thường",
      "description": "Tấn công thường\nThực hiện tối đa 5 lần chém liên tiếp.\nTrọng Kích\nDuy trì tiêu hao thể lực, chém nhanh liên tiếp.\n\nSau khi Trọng Kích kết thúc, sẽ bổ một nhát cực mạnh.\nNhảy Dậm\nĐáp xuống đất từ trên không, tấn công kẻ địch trên đường và gây sát thương phạm vi.",
      "upgrades": [
        {
          "name": "Sát Thương Lần 1",
          "value": "71.1%"
        },
        {
          "name": "Sát Thương Lần 2",
          "value": "70.9%"
        },
        {
          "name": "Sát Thương Lần 3",
          "value": "88.3%"
        },
        {
          "name": "Sát Thương Lần 4",
          "value": "86.5%"
        },
        {
          "name": "Sát Thương Lần 5",
          "value": "112%"
        },
        {
          "name": "Sát Thương Trọng Kích Tuần Hoàn",
          "value": "56.2%"
        },
        {
          "name": "Sát Thương Trọng Kích Chí Mạng",
          "value": "102%"
        },
        {
          "name": "Thể lực Trọng Kích tiêu hao",
          "value": "40/s"
        },
        {
          "name": "Thời Gian Tối Đa",
          "value": "5s"
        },
        {
          "name": "Sát Thương Khi Rơi",
          "value": "74.6%"
        },
        {
          "name": "Sát Thương Khi Rơi Từ Độ Cao Thấp/Cao",
          "value": "149% / 186%"
        }
      ]
    },
    {
      "name": "Bắt Sóng",
      "unlock": "Kỹ Năng Nguyên Tố",
      "description": "Không có gì phải lo lắng. Nếu có ai dám ra tay với cô hoặc người của cô, thì sẽ phải trả giá gấp 10 lần bằng sấm sét và kiếm.\nNhấn\nTích tụ sức mạnh sấm sét, chém mạnh kiếm lớn về phía trước, gây Sát Thương Nguyên Tố Lôi.\nNhấn Giữ\nNhấc vũ khí lên hình thành khiên, hấp thụ lượng sát thương căn cứ theo giới hạn HP của Beidou.\n\nSau khi thả giữ kỹ năng hoặc hết thời gian, sẽ vung kiếm giải phóng sức mạnh tích lũy để phản công, gây Sát Thương Nguyên Tố Lôi. Dựa vào số lần bị tấn công trong thời gian kỹ năng, tăng sát thương tạo thành. Kích hoạt 2 lần sẽ đạt buff sát thương cao nhất.\n\nKhiên có hiệu quả như sau:\n\nĐối với Sát Thương Nguyên Tố Lôi có 250% hiệu quả hấp thu.\nThi triển Nguyên Tố Lôi kèm theo cho Beidou.",
      "upgrades": [
        {
          "name": "Khiên hấp thụ",
          "value": "14.4% Max HP + 1386"
        },
        {
          "name": "Sát Thương Cơ Bản",
          "value": "122%"
        },
        {
          "name": "ST Tăng Sau Khi Nhận Tấn Công",
          "value": "160%"
        },
        {
          "name": "CD",
          "value": "7.5s"
        }
      ]
    },
    {
      "name": "Chước Lôi",
      "unlock": "Kỹ Năng Nộ",
      "description": "Nhớ lại trận chiến diệt Cự Thú Hải Sơn, triệu hồi cự thú và sức mạnh lôi điện, tạo ra Khiên Lôi Thú bao quanh, đồng thời gây Sát Thương Nguyên Tố Lôi cho kẻ địch xung quanh\nKhiên Lôi Thú\n\nKhi tấn công thường và trọng kích đánh trúng địch, giải phóng sức mạnh sấm sét, tạo 1 tia sét chạy giữa địch, gây Sát Thương Nguyên Tố Lôi.\nTăng khả năng kháng gián đoạn của nhân vật và giảm sát thương phải chịu.\nMỗi giây tối đa kích hoạt 1 tia sét.",
      "upgrades": [
        {
          "name": "Sát Thương Kỹ Năng",
          "value": "122%"
        },
        {
          "name": "Sát Thương Sấm Sét",
          "value": "96%"
        },
        {
          "name": "Miễn Sát Thương",
          "value": "20%"
        },
        {
          "name": "Thời Gian Kéo Dài",
          "value": "15s"
        },
        {
          "name": "CD",
          "value": "20s"
        },
        {
          "name": "Năng Lượng Nguyên Tố",
          "value": "80"
        }
      ]
    }
  ],
  "passiveTalents": [
    {
      "name": "Hào Quang Rực Rỡ",
      "unlock": "Đột phá 1 sao",
      "description": "Khi bị tấn công lập tức thi triển Bắt Sóng phản đòn, có buff sát thương cao nhất."
    },
    {
      "name": "Sấm Sét Đầy Trời",
      "unlock": "Đột phá 4 sao",
      "description": "Trong 10s sau khi thi triển Bắt Sóng, nhận được hiệu quả như sau:\nSát thương trọng kích và tấn công thường tạo thành tăng 15%, tốc độ tấn công tăng 15%.\nGiảm thời gian chuẩn bị cần thiết cho trọng kích."
    },
    {
      "name": "Sóng Vỗ Dào Dạt",
      "unlock": "Đột phá tự động",
      "description": "Giảm 20% tiêu hao thể lực cho toàn thành viên đội khi bơi."
    }
  ],
  "constellations": [
    {
      "name": "Ngư Long Trầm Tứ Phương",
      "unlock": "Cung Mệnh 1",
      "description": "Khi thi triển Chước Lôi: \nHình thành tấm khiên hấp thu sức mạnh tương đương với 16% giới hạn máu của Beidou, duy trì 15 giây.\nTăng 250% hiệu quả khiên đối với sát thương nguyên tố Lôi."
    },
    {
      "name": "Tia Sét Chói Lọi",
      "unlock": "Cung Mệnh 2",
      "description": "Chước Lôi có khả năng hất văng thêm 2 kẻ địch."
    },
    {
      "name": "Thủy Triều Dẫn Điện",
      "unlock": "Cung Mệnh 3",
      "description": "Tăng 3 cấp cho Bắt Sóng.\nTối đa là 15 cấp."
    },
    {
      "name": "Sao Trời Dẫn Lối",
      "unlock": "Cung Mệnh 4",
      "description": "Trong 10 giây sau khi bị kẻ địch tấn công Beidou sẽ được tăng thêm 20% sát thương nguyên tố Lôi."
    },
    {
      "name": "Đạp Lãng Liên Cấp",
      "unlock": "Cung Mệnh 5",
      "description": "Tăng 3 cấp cho Chước Lôi.\nTối đa là 15 cấp."
    },
    {
      "name": "Beidou Diệt Ác",
      "unlock": "Cung Mệnh 6",
      "description": "Trong thời gian Chước lôi tồn tại kháng nguyên tố Lôi của những kẻ địch xung quanh giảm 15%."
    }
  ]
}
